nitrain/__init__.py
nitrain/datasets/__init__.py
nitrain/datasets/dataset.py
nitrain/datasets/google_cloud.py
nitrain/datasets/utils.py
nitrain/explainers/__init__.py
nitrain/explainers/occlusion.py
nitrain/loaders/__init__.py
nitrain/loaders/loader.py
nitrain/models/__init__.py
nitrain/models/fetch_architecture.py
nitrain/models/fetch_pretrained.py
nitrain/predictors/__init__.py
nitrain/predictors/predictor.py
nitrain/readers/__init__.py
nitrain/readers/column.py
nitrain/readers/compose.py
nitrain/readers/folder_name.py
nitrain/readers/image.py
nitrain/readers/memory.py
nitrain/readers/utils.py
nitrain/samplers/__init__.py
nitrain/samplers/base.py
nitrain/samplers/block.py
nitrain/samplers/patch.py
nitrain/samplers/slice.py
nitrain/samplers/slice_patch.py
nitrain/trainers/__init__.py
nitrain/trainers/trainer.py
nitrain/transforms/__init__.py
nitrain/transforms/base.py
nitrain/transforms/image.py
nitrain/transforms/intensity.py
nitrain/transforms/labels.py
nitrain/transforms/math.py
nitrain/transforms/shape.py
nitrain/transforms/spatial.py
nitrain/transforms/spatial_random.py
nitrain/transforms/utility.py
nitrain/utils.py
nitrain-0.3.1.dist-info/LICENSE
nitrain-0.3.1.dist-info/METADATA
nitrain-0.3.1.dist-info/WHEEL
nitrain-0.3.1.dist-info/RECORD
