Metadata-Version: 2.1
Name: nitrain
Version: 0.3.1
Summary: Train medical imaging AI models locally or in the cloud with any framework
License: MIT
Author: ncullen93
Author-email: nicholas.cullen@med.lu.se
Requires-Python: >=3.9,<4.0
Classifier: License :: OSI Approved :: MIT License
Classifier: Programming Language :: Python :: 3
Classifier: Programming Language :: Python :: 3.9
Classifier: Programming Language :: Python :: 3.10
Classifier: Programming Language :: Python :: 3.11
Classifier: Programming Language :: Python :: 3.12
Requires-Dist: antspyx (>=0.5.3,<0.6.0)
Requires-Dist: parse (>=1.20.1,<2.0.0)
Requires-Dist: pydot (>=2.0.0,<3.0.0)
Requires-Dist: tqdm (>=4.66.2,<5.0.0)
